<?xml version="1.0" encoding="UTF-8"?>
<objects serializationModel="Studio.02.02.00">
	<object class="AudioFile" id="{93529172-f6ee-446e-9223-3f81736abc37}">
		<property name="assetPath">
			<value>toutch3.wav</value>
		</property>
		<property name="frequencyInKHz">
			<value>24</value>
		</property>
		<property name="channelCount">
			<value>2</value>
		</property>
		<property name="length">
			<value>1.7344166666666667</value>
		</property>
		<relationship name="masterAssetFolder">
			<destination>{20683148-dbd6-4140-801b-d17a7f1ab43d}</destination>
		</relationship>
	</object>
</objects>
